tictaco/__init__.py
tictaco/__version__.py
tictaco/tictaco.py
tictaco-0.1.1.dist-info/LICENSE
tictaco-0.1.1.dist-info/METADATA
tictaco-0.1.1.dist-info/WHEEL
tictaco-0.1.1.dist-info/entry_points.txt
tictaco-0.1.1.dist-info/top_level.txt
tictaco-0.1.1.dist-info/RECORD
