Metadata-Version: 2.1
Name: tictaco
Version: 0.1.1
Summary: Tic Tac Toe! 🌮
Home-page: https://github.com/vinayak-mehta/tictaco
Author: Vinayak Mehta
Author-email: vmehta94@gmail.com
License: Apache 2.0
Platform: UNKNOWN
Classifier: License :: OSI Approved :: Apache Software License
Classifier: Programming Language :: Python :: 3.6
Classifier: Programming Language :: Python :: 3.7
Classifier: Programming Language :: Python :: 3.8
Provides-Extra: dev
